iwave/__init__.py
iwave/const.py
iwave/data_models.py
iwave/dispersion.py
iwave/io.py
iwave/iwave.py
iwave/optimise.py
iwave/plots.py
iwave/sample_data.py
iwave/spectral.py
iwave/window.py
iwave-0.3.1.dist-info/licenses/LICENSE
iwave-0.3.1.dist-info/WHEEL
iwave-0.3.1.dist-info/METADATA
iwave-0.3.1.dist-info/RECORD
