Metadata-Version: 2.4
Name: iwave
Version: 0.3.1
Summary: IWaVE: Image-based Wave Velocimetry Estimation
Author-email: Giulio Dolcetti <giulio.dolcetti@unitn.it>, Salvador Pena Haro <pena@photrack.ch>, Hessel Winsemius <winsemius@rainbowsensing.com>
Requires-Python: >=3.10
Classifier: Development Status :: 1 - Planning
Classifier: Intended Audience :: Developers
Classifier: Intended Audience :: Science/Research
Classifier: Topic :: Scientific/Engineering :: Hydrology
Classifier: Topic :: Scientific/Engineering :: Image Processing
Classifier: License :: OSI Approved :: GNU Affero General Public License v3
Classifier: Programming Language :: Python :: 3
Classifier: Programming Language :: Python :: 3.10
Classifier: Programming Language :: Python :: 3.11
Classifier: Programming Language :: Python :: 3.12
License-File: LICENSE
Requires-Dist: matplotlib
Requires-Dist: numpy
Requires-Dist: numba
Requires-Dist: numexpr
Requires-Dist: opencv-python
Requires-Dist: rocket-fft
Requires-Dist: scipy
Requires-Dist: tqdm
Requires-Dist: iwave[extra] ; extra == "docs"
Requires-Dist: pydata-sphinx-theme ; extra == "docs"
Requires-Dist: sphinx ; extra == "docs"
Requires-Dist: sphinx_autosummary_accessors ; extra == "docs"
Requires-Dist: sphinx-design ; extra == "docs"
Requires-Dist: pooch ; extra == "extra"
Requires-Dist: matplotlib ; extra == "extra"
Requires-Dist: tqdm ; extra == "extra"
Requires-Dist: iwave[io, extra, dev, test, docs] ; extra == "full"
Requires-Dist: iwave[io] ; extra == "slim"
Requires-Dist: iwave[extra] ; extra == "test"
Requires-Dist: pytest ; extra == "test"
Requires-Dist: pytest-cov ; extra == "test"
Requires-Dist: pytest-lazy-fixtures ; extra == "test"
Project-URL: Source, https://github.com/DataForWater/IWaVE
Provides-Extra: docs
Provides-Extra: extra
Provides-Extra: full
Provides-Extra: io
Provides-Extra: slim
Provides-Extra: test
